pymakeutils/__init__.py
pymakeutils/common.py
pymakeutils/list_dependent_make_targets.py
pymakeutils/list_make_prerequisites.py
pymakeutils-1.4.0.dist-info/licenses/LICENSE
pymakeutils-1.4.0.dist-info/METADATA
pymakeutils-1.4.0.dist-info/WHEEL
pymakeutils-1.4.0.dist-info/entry_points.txt
pymakeutils-1.4.0.dist-info/top_level.txt
pymakeutils-1.4.0.dist-info/RECORD
