Metadata-Version: 2.4
Name: pymakeutils
Version: 1.4.0
Summary: CLI utilities to extract information from 'make -pq' output
Author-email: Luca Colagrande <colluca@iis.ee.ethz.ch>
License:                                  Apache License
Requires-Python: >=3.8
License-File: LICENSE
Requires-Dist: anytree
Dynamic: license-file
